{
  "runs": [
    {
      "id": "1kgaspda",
      "axis_label": "N-BEATSx + GFS"
    },
    {
      "id": "37d1qw62",
      "axis_label": "LSTM + GFS"
    },
    {
      "id": "37gqn5pu",
      "axis_label": "BiLSTM + GFS"
    },
    {
      "id": "7bk5e3eg",
      "axis_label": "TCN + GFS"
    },
    {
      "id": "20ooum9g",
      "axis_label": "TCNAttention + GFS"
    },
    {
      "id": "2upkj50k",
      "axis_label": "Transformer + GFS"
    },
    {
      "id": "323454hf",
      "axis_label": "Spacetimeformer + GFS"
    },
    {
      "id": "2ihek8mr",
      "axis_label": "Model naiwny"
    },
    {
      "id": "2wg9qa9m",
      "axis_label": "GFS"
    },
    {
      "id": "9lk4da2a",
      "axis_label": "Regresja liniowa"
    }
  ]
}
