{
  "runs": [
    {
      "id": "2v5251pd",
      "axis_label": "LSTM + GFS"
    },
    {
      "id": "2r8wt6pj",
      "axis_label": "BiLSTM + GFS"
    },
    {
      "id": "24fawz6y",
      "axis_label": "TCN + GFS"
    },
    {
      "id": "2sha2wwl",
      "axis_label": "TCN-Attention + GFS"
    },
    {
      "id": "bfdextfk",
      "axis_label": "Transformer + GFS"
    },
    {
      "id": "294oneq3",
      "axis_label": "Spacetimeformer + GFS"
    },
    {
      "id": "epurfgld",
      "axis_label": "N-BEATSx + GFS"
    },
    {
      "id": "k33i6h69",
      "axis_label": "Model naiwny"
    },
    {
      "id": "256u5i7o",
      "axis_label": "Regresja liniowa"
    },
    {
      "id": "2ref2cjt",
      "axis_label": "ARIMAX + GFS"
    },
    {
      "id": "1mriix6i",
      "axis_label": "GFS"
    }
  ]
}
